{
  "id": "dfaa5723-6f5e-47fe-b86d-2dc467f09390",
  "prevId": "894fe0ed-4612-4f48-bd5f-e206801a5416",
  "version": "7",
  "dialect": "postgresql",
  "tables": {
    "public.articles": {
      "name": "articles",
      "schema": "",
      "columns": {
        "id": {
          "name": "id",
          "type": "serial",
          "primaryKey": true,
          "notNull": true
        },
        "slug": {
          "name": "slug",
          "type": "text",
          "primaryKey": false,
          "notNull": true
        },
        "locale": {
          "name": "locale",
          "type": "text",
          "primaryKey": false,
          "notNull": true,
          "default": "'ja'"
        },
        "title": {
          "name": "title",
          "type": "text",
          "primaryKey": false,
          "notNull": true
        },
        "body": {
          "name": "body",
          "type": "text",
          "primaryKey": false,
          "notNull": true
        },
        "excerpt": {
          "name": "excerpt",
          "type": "text",
          "primaryKey": false,
          "notNull": false
        },
        "cover_image": {
          "name": "cover_image",
          "type": "text",
          "primaryKey": false,
          "notNull": false
        },
        "status": {
          "name": "status",
          "type": "text",
          "primaryKey": false,
          "notNull": true,
          "default": "'draft'"
        },
        "author_id": {
          "name": "author_id",
          "type": "integer",
          "primaryKey": false,
          "notNull": false
        },
        "created_at": {
          "name": "created_at",
          "type": "timestamp with time zone",
          "primaryKey": false,
          "notNull": true,
          "default": "now()"
        },
        "updated_at": {
          "name": "updated_at",
          "type": "timestamp with time zone",
          "primaryKey": false,
          "notNull": true,
          "default": "now()"
        },
        "published_at": {
          "name": "published_at",
          "type": "timestamp with time zone",
          "primaryKey": false,
          "notNull": false
        }
      },
      "indexes": {
        "idx_articles_status": {
          "name": "idx_articles_status",
          "columns": [
            {
              "expression": "status",
              "isExpression": false,
              "asc": true,
              "nulls": "last"
            }
          ],
          "isUnique": false,
          "concurrently": false,
          "method": "btree",
          "with": {}
        },
        "idx_articles_locale": {
          "name": "idx_articles_locale",
          "columns": [
            {
              "expression": "locale",
              "isExpression": false,
              "asc": true,
              "nulls": "last"
            }
          ],
          "isUnique": false,
          "concurrently": false,
          "method": "btree",
          "with": {}
        },
        "idx_articles_published": {
          "name": "idx_articles_published",
          "columns": [
            {
              "expression": "published_at",
              "isExpression": false,
              "asc": true,
              "nulls": "last"
            }
          ],
          "isUnique": false,
          "concurrently": false,
          "method": "btree",
          "with": {}
        }
      },
      "foreignKeys": {
        "articles_author_id_authors_id_fk": {
          "name": "articles_author_id_authors_id_fk",
          "tableFrom": "articles",
          "tableTo": "authors",
          "columnsFrom": [
            "author_id"
          ],
          "columnsTo": [
            "id"
          ],
          "onDelete": "set null",
          "onUpdate": "no action"
        }
      },
      "compositePrimaryKeys": {},
      "uniqueConstraints": {
        "articles_slug_unique": {
          "name": "articles_slug_unique",
          "nullsNotDistinct": false,
          "columns": [
            "slug"
          ]
        }
      },
      "policies": {},
      "checkConstraints": {},
      "isRLSEnabled": false
    },
    "public.authors": {
      "name": "authors",
      "schema": "",
      "columns": {
        "id": {
          "name": "id",
          "type": "serial",
          "primaryKey": true,
          "notNull": true
        },
        "email": {
          "name": "email",
          "type": "text",
          "primaryKey": false,
          "notNull": true
        },
        "name": {
          "name": "name",
          "type": "text",
          "primaryKey": false,
          "notNull": true
        },
        "avatar": {
          "name": "avatar",
          "type": "text",
          "primaryKey": false,
          "notNull": false
        },
        "bio": {
          "name": "bio",
          "type": "text",
          "primaryKey": false,
          "notNull": false
        },
        "created_at": {
          "name": "created_at",
          "type": "timestamp with time zone",
          "primaryKey": false,
          "notNull": true,
          "default": "now()"
        }
      },
      "indexes": {},
      "foreignKeys": {},
      "compositePrimaryKeys": {},
      "uniqueConstraints": {
        "authors_email_unique": {
          "name": "authors_email_unique",
          "nullsNotDistinct": false,
          "columns": [
            "email"
          ]
        }
      },
      "policies": {},
      "checkConstraints": {},
      "isRLSEnabled": false
    },
    "public.course_dates": {
      "name": "course_dates",
      "schema": "",
      "columns": {
        "id": {
          "name": "id",
          "type": "serial",
          "primaryKey": true,
          "notNull": true
        },
        "value": {
          "name": "value",
          "type": "text",
          "primaryKey": false,
          "notNull": true
        },
        "date": {
          "name": "date",
          "type": "text",
          "primaryKey": false,
          "notNull": false
        },
        "label_ja": {
          "name": "label_ja",
          "type": "text",
          "primaryKey": false,
          "notNull": true
        },
        "label_en": {
          "name": "label_en",
          "type": "text",
          "primaryKey": false,
          "notNull": false
        },
        "course_slug": {
          "name": "course_slug",
          "type": "text",
          "primaryKey": false,
          "notNull": true,
          "default": "'utsunomiya-meditation-course'"
        },
        "sort_order": {
          "name": "sort_order",
          "type": "integer",
          "primaryKey": false,
          "notNull": true,
          "default": 0
        },
        "is_active": {
          "name": "is_active",
          "type": "boolean",
          "primaryKey": false,
          "notNull": true,
          "default": true
        },
        "created_at": {
          "name": "created_at",
          "type": "timestamp with time zone",
          "primaryKey": false,
          "notNull": true,
          "default": "now()"
        },
        "updated_at": {
          "name": "updated_at",
          "type": "timestamp with time zone",
          "primaryKey": false,
          "notNull": true,
          "default": "now()"
        }
      },
      "indexes": {
        "idx_course_dates_active": {
          "name": "idx_course_dates_active",
          "columns": [
            {
              "expression": "is_active",
              "isExpression": false,
              "asc": true,
              "nulls": "last"
            }
          ],
          "isUnique": false,
          "concurrently": false,
          "method": "btree",
          "with": {}
        },
        "idx_course_dates_date": {
          "name": "idx_course_dates_date",
          "columns": [
            {
              "expression": "date",
              "isExpression": false,
              "asc": true,
              "nulls": "last"
            }
          ],
          "isUnique": false,
          "concurrently": false,
          "method": "btree",
          "with": {}
        }
      },
      "foreignKeys": {},
      "compositePrimaryKeys": {},
      "uniqueConstraints": {
        "course_dates_value_unique": {
          "name": "course_dates_value_unique",
          "nullsNotDistinct": false,
          "columns": [
            "value"
          ]
        }
      },
      "policies": {},
      "checkConstraints": {},
      "isRLSEnabled": false
    },
    "public.registrations": {
      "name": "registrations",
      "schema": "",
      "columns": {
        "id": {
          "name": "id",
          "type": "serial",
          "primaryKey": true,
          "notNull": true
        },
        "created_at": {
          "name": "created_at",
          "type": "timestamp with time zone",
          "primaryKey": false,
          "notNull": true,
          "default": "now()"
        },
        "course_slug": {
          "name": "course_slug",
          "type": "text",
          "primaryKey": false,
          "notNull": true,
          "default": "'utsunomiya-meditation-course'"
        },
        "session_date": {
          "name": "session_date",
          "type": "text",
          "primaryKey": false,
          "notNull": true
        },
        "email": {
          "name": "email",
          "type": "text",
          "primaryKey": false,
          "notNull": true
        },
        "full_name": {
          "name": "full_name",
          "type": "text",
          "primaryKey": false,
          "notNull": true
        },
        "furigana": {
          "name": "furigana",
          "type": "text",
          "primaryKey": false,
          "notNull": true
        },
        "gender": {
          "name": "gender",
          "type": "text",
          "primaryKey": false,
          "notNull": true
        },
        "nationality": {
          "name": "nationality",
          "type": "text",
          "primaryKey": false,
          "notNull": true
        },
        "prefecture": {
          "name": "prefecture",
          "type": "text",
          "primaryKey": false,
          "notNull": false
        },
        "phone": {
          "name": "phone",
          "type": "text",
          "primaryKey": false,
          "notNull": false
        },
        "referral_source": {
          "name": "referral_source",
          "type": "text",
          "primaryKey": false,
          "notNull": true
        },
        "photo_consent": {
          "name": "photo_consent",
          "type": "text",
          "primaryKey": false,
          "notNull": true
        },
        "locale": {
          "name": "locale",
          "type": "text",
          "primaryKey": false,
          "notNull": true,
          "default": "'ja'"
        },
        "handled": {
          "name": "handled",
          "type": "boolean",
          "primaryKey": false,
          "notNull": true,
          "default": false
        }
      },
      "indexes": {
        "idx_registrations_session": {
          "name": "idx_registrations_session",
          "columns": [
            {
              "expression": "session_date",
              "isExpression": false,
              "asc": true,
              "nulls": "last"
            }
          ],
          "isUnique": false,
          "concurrently": false,
          "method": "btree",
          "with": {}
        },
        "idx_registrations_created": {
          "name": "idx_registrations_created",
          "columns": [
            {
              "expression": "created_at",
              "isExpression": false,
              "asc": true,
              "nulls": "last"
            }
          ],
          "isUnique": false,
          "concurrently": false,
          "method": "btree",
          "with": {}
        }
      },
      "foreignKeys": {},
      "compositePrimaryKeys": {},
      "uniqueConstraints": {},
      "policies": {},
      "checkConstraints": {},
      "isRLSEnabled": false
    },
    "public.users": {
      "name": "users",
      "schema": "",
      "columns": {
        "id": {
          "name": "id",
          "type": "serial",
          "primaryKey": true,
          "notNull": true
        },
        "email": {
          "name": "email",
          "type": "text",
          "primaryKey": false,
          "notNull": true
        },
        "name": {
          "name": "name",
          "type": "text",
          "primaryKey": false,
          "notNull": false
        },
        "avatar": {
          "name": "avatar",
          "type": "text",
          "primaryKey": false,
          "notNull": false
        },
        "author_id": {
          "name": "author_id",
          "type": "integer",
          "primaryKey": false,
          "notNull": false
        },
        "is_active": {
          "name": "is_active",
          "type": "boolean",
          "primaryKey": false,
          "notNull": true,
          "default": true
        },
        "is_admin": {
          "name": "is_admin",
          "type": "boolean",
          "primaryKey": false,
          "notNull": true,
          "default": false
        },
        "blog_role": {
          "name": "blog_role",
          "type": "text",
          "primaryKey": false,
          "notNull": true,
          "default": "'none'"
        },
        "can_manage_registrations": {
          "name": "can_manage_registrations",
          "type": "boolean",
          "primaryKey": false,
          "notNull": true,
          "default": false
        },
        "can_manage_course_dates": {
          "name": "can_manage_course_dates",
          "type": "boolean",
          "primaryKey": false,
          "notNull": true,
          "default": false
        },
        "notify_registrations": {
          "name": "notify_registrations",
          "type": "boolean",
          "primaryKey": false,
          "notNull": true,
          "default": false
        },
        "created_at": {
          "name": "created_at",
          "type": "timestamp with time zone",
          "primaryKey": false,
          "notNull": true,
          "default": "now()"
        }
      },
      "indexes": {},
      "foreignKeys": {
        "users_author_id_authors_id_fk": {
          "name": "users_author_id_authors_id_fk",
          "tableFrom": "users",
          "tableTo": "authors",
          "columnsFrom": [
            "author_id"
          ],
          "columnsTo": [
            "id"
          ],
          "onDelete": "set null",
          "onUpdate": "no action"
        }
      },
      "compositePrimaryKeys": {},
      "uniqueConstraints": {
        "users_email_unique": {
          "name": "users_email_unique",
          "nullsNotDistinct": false,
          "columns": [
            "email"
          ]
        }
      },
      "policies": {},
      "checkConstraints": {},
      "isRLSEnabled": false
    }
  },
  "enums": {},
  "schemas": {},
  "sequences": {},
  "roles": {},
  "policies": {},
  "views": {},
  "_meta": {
    "columns": {},
    "schemas": {},
    "tables": {}
  }
}